python_tsp/__init__.py
python_tsp/distances/__init__.py
python_tsp/distances/data_processing.py
python_tsp/distances/euclidean_distance.py
python_tsp/distances/great_circle_distance.py
python_tsp/distances/osrm_distance.py
python_tsp/distances/tsplib_distance.py
python_tsp/exact/__init__.py
python_tsp/exact/branch_and_bound/__init__.py
python_tsp/exact/branch_and_bound/node.py
python_tsp/exact/branch_and_bound/priority_queue.py
python_tsp/exact/branch_and_bound/solver.py
python_tsp/exact/brute_force.py
python_tsp/exact/dynamic_programming.py
python_tsp/heuristics/__init__.py
python_tsp/heuristics/lin_kernighan.py
python_tsp/heuristics/local_search.py
python_tsp/heuristics/perturbation_schemes.py
python_tsp/heuristics/record_to_record.py
python_tsp/heuristics/simulated_annealing.py
python_tsp/utils/__init__.py
python_tsp/utils/permutation_distance.py
python_tsp/utils/setup_initial_solution.py
python_tsp-0.4.2.dist-info/LICENSE
python_tsp-0.4.2.dist-info/METADATA
python_tsp-0.4.2.dist-info/WHEEL
python_tsp-0.4.2.dist-info/RECORD
