Metadata-Version: 2.1
Name: python_tsp
Version: 0.4.2
Summary: Library to solve the Traveling Salesperson Problem in pure Python.
Home-page: https://github.com/fillipe-gsm/python-tsp
License: MIT
Author: Fillipe Goulart
Author-email: fillipe.gsm@tutanota.com
Requires-Python: >=3.9,<4.0
Classifier: License :: OSI Approved :: MIT License
Classifier: Programming Language :: Python :: 3
Classifier: Programming Language :: Python :: 3.9
Classifier: Programming Language :: Python :: 3.10
Classifier: Programming Language :: Python :: 3.11
Classifier: Programming Language :: Python :: 3.12
Requires-Dist: numpy (>=1.26.3,<2.0.0)
Requires-Dist: requests (>=2.28.0,<3.0.0)
Requires-Dist: tsplib95 (>=0.7.1,<0.8.0)
Project-URL: Repository, https://github.com/fillipe-gsm/python-tsp
